jwks/__init__.py
jwks/errors.py
jwks/jwks.py
jwks/singleton.py
jwks-1.0.0.dist-info/METADATA
jwks-1.0.0.dist-info/WHEEL
jwks-1.0.0.dist-info/top_level.txt
jwks-1.0.0.dist-info/RECORD
