Metadata-Version: 2.1
Name: jwks
Version: 1.0.0
Summary: A lightweight Python library for using JSON Web Key Sets
Home-page: https://github.com/marpaia/jwks
Author: Mike Arpaia
Author-email: mike@arpaia.co
License: MIT
Platform: UNKNOWN
Classifier: License :: OSI Approved :: MIT License
Classifier: Programming Language :: Python :: 3
Classifier: Programming Language :: Python :: 3.9
Requires-Dist: jose
Requires-Dist: pydantic
Requires-Dist: requests
